Final.srcs/sources_1/new/data_mem.v
`timescale 1ns / 1ps
(* dont_touch = "true" *)
module data_mem (
    input  wire        clk, mem_read, mem_write,
    input  wire [31:0] addr, wd,
    input  wire [2:0]  funct3,
    output reg  [31:0] rd
);
    (* ram_style = "block" *)
    reg [31:0] mem [0:255];

    integer i;
    initial begin
        for (i = 0; i < 256; i = i + 1)
            mem[i] = 32'b0;
    end

    always @(posedge clk) begin
        if (mem_write) begin
            case (funct3)
                3'b000: mem[addr[9:2]] <= {mem[addr[9:2]][31:8],  wd[7:0]};
                3'b001: mem[addr[9:2]] <= {mem[addr[9:2]][31:16], wd[15:0]};
                3'b010: mem[addr[9:2]] <= wd;
                default: ;
            endcase
        end
    end

    always @(*) begin
        if (mem_read) begin
            case (funct3)
                3'b000: rd = {{24{mem[addr[9:2]][7]}},  mem[addr[9:2]][7:0]};
                3'b001: rd = {{16{mem[addr[9:2]][15]}}, mem[addr[9:2]][15:0]};
                3'b010: rd = mem[addr[9:2]];
                3'b100: rd = {24'b0, mem[addr[9:2]][7:0]};
                3'b101: rd = {16'b0, mem[addr[9:2]][15:0]};
                default: rd = 32'b0;
            endcase
        end else rd = 32'b0;
    end
endmodule

Final.srcs/sources_1/new/alu.v
`timescale 1ns / 1ps
(* dont_touch = "true" *)
module alu (
    input  wire [31:0] a, b,
    input  wire [3:0]  alu_ctrl,
    output reg  [31:0] result,
    output wire        zero
);
    always @(*) begin
        case (alu_ctrl)
            4'd0:  result = a + b;
            4'd1:  result = a - b;
            4'd2:  result = a & b;
            4'd3:  result = a | b;
            4'd4:  result = a ^ b;
            4'd5:  result = a << b[4:0];
            4'd6:  result = a >> b[4:0];
            4'd7:  result = $signed(a) >>> b[4:0];
            4'd8:  result = ($signed(a) < $signed(b)) ? 32'd1 : 32'd0;
            4'd9:  result = (a < b) ? 32'd1 : 32'd0;
            4'd10: result = b;
            default: result = 32'b0;
        endcase
    end
    assign zero = (result == 32'b0);
endmodule

Final.srcs/sources_1/new/forwarding_unit.v
`timescale 1ns / 1ps
(* dont_touch = "true" *)
module forwarding_unit (
    input  wire [4:0]  ex_mem_rd, mem_wb_rd,
    input  wire [4:0]  id_ex_rs1, id_ex_rs2,
    input  wire        ex_mem_reg_write, mem_wb_reg_write,
    output reg  [1:0]  forward_a, forward_b
);
    always @(*) begin
        if (ex_mem_reg_write && (ex_mem_rd != 5'b0) && (ex_mem_rd == id_ex_rs1))
            forward_a = 2'b10;
        else if (mem_wb_reg_write && (mem_wb_rd != 5'b0) && (mem_wb_rd == id_ex_rs1))
            forward_a = 2'b01;
        else forward_a = 2'b00;

        if (ex_mem_reg_write && (ex_mem_rd != 5'b0) && (ex_mem_rd == id_ex_rs2))
            forward_b = 2'b10;
        else if (mem_wb_reg_write && (mem_wb_rd != 5'b0) && (mem_wb_rd == id_ex_rs2))
            forward_b = 2'b01;
        else forward_b = 2'b00;
    end
endmodule

Final.srcs/sources_1/new/hazard_unit.v
`timescale 1ns / 1ps
(* dont_touch = "true" *)
module hazard_unit (
    input  wire        id_ex_mem_read,
    input  wire [4:0]  id_ex_rd, if_id_rs1, if_id_rs2,
    output wire        stall
);
    assign stall = id_ex_mem_read &&
                   ((id_ex_rd == if_id_rs1) || (id_ex_rd == if_id_rs2));
endmodule

Final.srcs/sources_1/new/control_unit.v
`timescale 1ns / 1ps
(* dont_touch = "true" *)
module control_unit (
    input  wire [6:0] opcode, funct7,
    input  wire [2:0] funct3,
    output reg  [3:0] alu_op,
    output reg        alu_src, mem_read, mem_write,
                      reg_write, mem_to_reg
);
    always @(*) begin
        alu_op    = 4'b0; alu_src   = 1'b0;
        mem_read  = 1'b0; mem_write = 1'b0;
        reg_write = 1'b0; mem_to_reg= 1'b0;
        case (opcode)
            7'b0110011: begin
                reg_write = 1'b1;
                case ({funct7[5], funct3})
                    4'b0000: alu_op = 4'd0;
                    4'b1000: alu_op = 4'd1;
                    4'b0111: alu_op = 4'd2;
                    4'b0110: alu_op = 4'd3;
                    4'b0100: alu_op = 4'd4;
                    4'b0001: alu_op = 4'd5;
                    4'b0101: alu_op = 4'd6;
                    4'b1101: alu_op = 4'd7;
                    4'b0010: alu_op = 4'd8;
                    4'b0011: alu_op = 4'd9;
                    default: alu_op = 4'd0;
                endcase
            end
            7'b0010011: begin
                alu_src = 1'b1; reg_write = 1'b1;
                case (funct3)
                    3'b000: alu_op = 4'd0;
                    3'b111: alu_op = 4'd2;
                    3'b110: alu_op = 4'd3;
                    3'b100: alu_op = 4'd4;
                    3'b001: alu_op = 4'd5;
                    3'b101: alu_op = funct7[5] ? 4'd7 : 4'd6;
                    3'b010: alu_op = 4'd8;
                    3'b011: alu_op = 4'd9;
                    default: alu_op = 4'd0;
                endcase
            end
            7'b0000011: begin
                alu_src=1'b1; mem_read=1'b1;
                reg_write=1'b1; mem_to_reg=1'b1; alu_op=4'd0;
            end
            7'b0100011: begin
                alu_src=1'b1; mem_write=1'b1; alu_op=4'd0;
            end
            7'b0110111: begin
                alu_src=1'b1; reg_write=1'b1; alu_op=4'd10;
            end
            7'b0010111: begin
                alu_src=1'b1; reg_write=1'b1; alu_op=4'd0;
            end
            default: begin
                alu_op=4'd0; alu_src=1'b0;
                mem_read=1'b0; mem_write=1'b0;
                reg_write=1'b0; mem_to_reg=1'b0;
            end
        endcase
    end
endmodule

Final.srcs/sources_1/new/imm_gen.v
`timescale 1ns / 1ps
(* dont_touch = "true" *)
module imm_gen (
    input  wire [31:0] instr,
    output reg  [31:0] imm
);
    wire [6:0] opcode = instr[6:0];
    always @(*) begin
        case (opcode)
            7'b0010011,
            7'b0000011: imm = {{20{instr[31]}}, instr[31:20]};
            7'b0100011: imm = {{20{instr[31]}}, instr[31:25], instr[11:7]};
            7'b1100011: imm = {{19{instr[31]}}, instr[31], instr[7],
                                instr[30:25], instr[11:8], 1'b0};
            7'b0110111,
            7'b0010111: imm = {instr[31:12], 12'b0};
            7'b1101111: imm = {{11{instr[31]}}, instr[31], instr[19:12],
                                instr[20], instr[30:21], 1'b0};
            default:    imm = 32'b0;
        endcase
    end
endmodule

Final.srcs/sources_1/new/reg_file.v
`timescale 1ns / 1ps
(* dont_touch = "true" *)
module reg_file (
    input  wire        clk,
    input  wire        we,
    input  wire [4:0]  rs1, rs2, rd,
    input  wire [31:0] wd,
    output wire [31:0] rs1_data, rs2_data,
    output wire [31:0] reg3_out,
    output wire [31:0] reg4_out,
    output wire [31:0] reg5_out,
    output wire [31:0] reg6_out,
    output wire [31:0] reg7_out,
    output wire [31:0] reg8_out
);
    (* dont_touch = "true" *)
    reg [31:0] regs [0:31];

    integer i;
    initial begin
        for (i = 0; i < 32; i = i + 1)
            regs[i] = 32'b0;
    end

    always @(posedge clk) begin
        if (we && rd != 5'b0)
            regs[rd] <= wd;
    end

    assign rs1_data = (rs1 == 5'b0) ? 32'b0 : regs[rs1];
    assign rs2_data = (rs2 == 5'b0) ? 32'b0 : regs[rs2];
    assign reg3_out = regs[3];
    assign reg4_out = regs[4];
    assign reg5_out = regs[5];
    assign reg6_out = regs[6];
    assign reg7_out = regs[7];
    assign reg8_out = regs[8];
endmodule

Final.srcs/sources_1/new/instr_mem.v
`timescale 1ns / 1ps
(* dont_touch = "true" *)
module instr_mem (
    input  wire        clk,
    input  wire [31:0] addr,
    output wire [31:0] instr
);
    (* rom_style = "block" *)
    reg [31:0] mem [0:255];

    integer k;
    initial begin
        for (k = 0; k < 256; k = k + 1)
            mem[k] = 32'h00000013;
        $readmemh("D:/Xilink/SoC/GEMINI/project_1/project_1.sim/sim_1/behav/xsim/program.hex", mem);
    end

    assign instr = mem[addr[9:2]];
endmodule

Final.srcs/sources_1/new/pc_reg.v
`timescale 1ns / 1ps
(* dont_touch = "true" *)
module pc_reg (
    input  wire        clk,
    input  wire        rst,
    input  wire        stall,
    input  wire [31:0] pc_next,
    output reg  [31:0] pc_out
);
    always @(posedge clk or posedge rst) begin
        if (rst)
            pc_out <= 32'h00000000;
        else if (!stall)
            pc_out <= pc_next;
    end
endmodule

Final.srcs/sources_1/new/rv32i_pipeline.v
`timescale 1ns / 1ps
(* dont_touch = "true" *)
module rv32i_pipeline (
    input  wire        clk,
    input  wire        rst,
    input  wire [1:0]  sw,
    output wire [3:0]  led
);

(* dont_touch = "true" *) reg [31:0] IF_ID_PC, IF_ID_IR;
(* dont_touch = "true" *) reg [31:0] ID_EX_PC, ID_EX_RS1, ID_EX_RS2, ID_EX_IMM;
(* dont_touch = "true" *) reg [4:0]  ID_EX_RD, ID_EX_RS1_ADDR, ID_EX_RS2_ADDR;
(* dont_touch = "true" *) reg [3:0]  ID_EX_ALU_OP;
(* dont_touch = "true" *) reg        ID_EX_ALU_SRC, ID_EX_MEM_READ, ID_EX_MEM_WRITE;
(* dont_touch = "true" *) reg        ID_EX_REG_WRITE, ID_EX_MEM_TO_REG;
(* dont_touch = "true" *) reg [2:0]  ID_EX_FUNCT3;
(* dont_touch = "true" *) reg [31:0] EX_MEM_ALU_RES, EX_MEM_RS2;
(* dont_touch = "true" *) reg [4:0]  EX_MEM_RD;
(* dont_touch = "true" *) reg        EX_MEM_MEM_READ, EX_MEM_MEM_WRITE;
(* dont_touch = "true" *) reg        EX_MEM_REG_WRITE, EX_MEM_MEM_TO_REG;
(* dont_touch = "true" *) reg [2:0]  EX_MEM_FUNCT3;
(* dont_touch = "true" *) reg        EX_MEM_ZERO;
(* dont_touch = "true" *) reg [31:0] MEM_WB_MEM_DATA, MEM_WB_ALU_RES;
(* dont_touch = "true" *) reg [4:0]  MEM_WB_RD;
(* dont_touch = "true" *) reg        MEM_WB_REG_WRITE, MEM_WB_MEM_TO_REG;

wire [31:0] pc_out, pc_next, pc_plus4;
wire [31:0] instr;
wire [31:0] rs1_data, rs2_data, imm_ext;
wire [31:0] alu_in_b, alu_result;
wire [31:0] mem_read_data;
wire [31:0] wb_data;
wire [31:0] reg3_out, reg4_out, reg5_out, reg6_out, reg7_out, reg8_out;
wire        alu_zero;
wire [3:0]  alu_ctrl;
wire        alu_src_ctrl, mem_read_ctrl, mem_write_ctrl;
wire        reg_write_ctrl, mem_to_reg_ctrl;
wire [1:0]  forward_a, forward_b;
wire        stall;
wire [4:0]  rd_id, rs1_id, rs2_id;
wire [2:0]  funct3;
wire [6:0]  opcode, funct7;

assign opcode = IF_ID_IR[6:0];
assign rd_id  = IF_ID_IR[11:7];
assign funct3 = IF_ID_IR[14:12];
assign rs1_id = IF_ID_IR[19:15];
assign rs2_id = IF_ID_IR[24:20];
assign funct7 = IF_ID_IR[31:25];

// ============================================================
// IF Stage
// ============================================================
pc_reg PC (
    .clk(clk), .rst(rst), .stall(stall),
    .pc_next(pc_next), .pc_out(pc_out)
);
assign pc_plus4 = pc_out + 32'd4;
assign pc_next  = pc_plus4;

instr_mem IMEM (
    .clk(clk), .addr(pc_out), .instr(instr)
);

always @(posedge clk or posedge rst) begin
    if (rst) begin
        IF_ID_PC <= 32'b0;
        IF_ID_IR <= 32'h00000013;
    end else if (!stall) begin
        IF_ID_PC <= pc_out;
        IF_ID_IR <= instr;
    end
end

// ============================================================
// ID Stage
// ============================================================
reg_file RF (
    .clk(clk),
    .rs1(rs1_id), .rs2(rs2_id),
    .rd(MEM_WB_RD), .wd(wb_data), .we(MEM_WB_REG_WRITE),
    .rs1_data(rs1_data), .rs2_data(rs2_data),
    .reg3_out(reg3_out), .reg4_out(reg4_out),
    .reg5_out(reg5_out), .reg6_out(reg6_out),
    .reg7_out(reg7_out), .reg8_out(reg8_out)
);

imm_gen IMMGEN (
    .instr(IF_ID_IR), .imm(imm_ext)
);

control_unit CU (
    .opcode(opcode), .funct3(funct3), .funct7(funct7),
    .alu_op(alu_ctrl), .alu_src(alu_src_ctrl),
    .mem_read(mem_read_ctrl), .mem_write(mem_write_ctrl),
    .reg_write(reg_write_ctrl), .mem_to_reg(mem_to_reg_ctrl)
);

hazard_unit HU (
    .id_ex_mem_read(ID_EX_MEM_READ),
    .id_ex_rd(ID_EX_RD),
    .if_id_rs1(rs1_id), .if_id_rs2(rs2_id),
    .stall(stall)
);

always @(posedge clk or posedge rst) begin
    if (rst || stall) begin
        ID_EX_RS1       <= 32'b0;
        ID_EX_RS2       <= 32'b0;
        ID_EX_IMM       <= 32'b0;
        ID_EX_RD        <= 5'b0;
        ID_EX_RS1_ADDR  <= 5'b0;
        ID_EX_RS2_ADDR  <= 5'b0;
        ID_EX_ALU_OP    <= 4'b0;
        ID_EX_ALU_SRC   <= 1'b0;
        ID_EX_MEM_READ  <= 1'b0;
        ID_EX_MEM_WRITE <= 1'b0;
        ID_EX_REG_WRITE <= 1'b0;
        ID_EX_MEM_TO_REG<= 1'b0;
        ID_EX_FUNCT3    <= 3'b0;
        ID_EX_PC        <= 32'b0;
    end else begin
        ID_EX_PC        <= IF_ID_PC;
        ID_EX_RS1       <= rs1_data;
        ID_EX_RS2       <= rs2_data;
        ID_EX_IMM       <= imm_ext;
        ID_EX_RD        <= rd_id;
        ID_EX_RS1_ADDR  <= rs1_id;
        ID_EX_RS2_ADDR  <= rs2_id;
        ID_EX_ALU_OP    <= alu_ctrl;
        ID_EX_ALU_SRC   <= alu_src_ctrl;
        ID_EX_MEM_READ  <= mem_read_ctrl;
        ID_EX_MEM_WRITE <= mem_write_ctrl;
        ID_EX_REG_WRITE <= reg_write_ctrl;
        ID_EX_MEM_TO_REG<= mem_to_reg_ctrl;
        ID_EX_FUNCT3    <= funct3;
    end
end

// ============================================================
// EX Stage
// ============================================================
forwarding_unit FU (
    .ex_mem_rd(EX_MEM_RD), .mem_wb_rd(MEM_WB_RD),
    .id_ex_rs1(ID_EX_RS1_ADDR), .id_ex_rs2(ID_EX_RS2_ADDR),
    .ex_mem_reg_write(EX_MEM_REG_WRITE),
    .mem_wb_reg_write(MEM_WB_REG_WRITE),
    .forward_a(forward_a), .forward_b(forward_b)
);

wire [31:0] fwd_rs1 = (forward_a == 2'b10) ? EX_MEM_ALU_RES :
                      (forward_a == 2'b01) ? wb_data : ID_EX_RS1;
wire [31:0] fwd_rs2 = (forward_b == 2'b10) ? EX_MEM_ALU_RES :
                      (forward_b == 2'b01) ? wb_data : ID_EX_RS2;

assign alu_in_b = ID_EX_ALU_SRC ? ID_EX_IMM : fwd_rs2;

alu ALU (
    .a(fwd_rs1), .b(alu_in_b),
    .alu_ctrl(ID_EX_ALU_OP),
    .result(alu_result), .zero(alu_zero)
);

always @(posedge clk or posedge rst) begin
    if (rst) begin
        EX_MEM_ALU_RES   <= 32'b0;
        EX_MEM_RS2       <= 32'b0;
        EX_MEM_RD        <= 5'b0;
        EX_MEM_ZERO      <= 1'b0;
        EX_MEM_MEM_READ  <= 1'b0;
        EX_MEM_MEM_WRITE <= 1'b0;
        EX_MEM_REG_WRITE <= 1'b0;
        EX_MEM_MEM_TO_REG<= 1'b0;
        EX_MEM_FUNCT3    <= 3'b0;
    end else begin
        EX_MEM_ALU_RES   <= alu_result;
        EX_MEM_RS2       <= fwd_rs2;
        EX_MEM_RD        <= ID_EX_RD;
        EX_MEM_MEM_READ  <= ID_EX_MEM_READ;
        EX_MEM_MEM_WRITE <= ID_EX_MEM_WRITE;
        EX_MEM_REG_WRITE <= ID_EX_REG_WRITE;
        EX_MEM_MEM_TO_REG<= ID_EX_MEM_TO_REG;
        EX_MEM_FUNCT3    <= ID_EX_FUNCT3;
        EX_MEM_ZERO      <= alu_zero;
    end
end

// ============================================================
// MEM Stage
// ============================================================
data_mem DMEM (
    .clk(clk),
    .addr(EX_MEM_ALU_RES), .wd(EX_MEM_RS2),
    .mem_read(EX_MEM_MEM_READ), .mem_write(EX_MEM_MEM_WRITE),
    .funct3(EX_MEM_FUNCT3), .rd(mem_read_data)
);

always @(posedge clk or posedge rst) begin
    if (rst) begin
        MEM_WB_MEM_DATA   <= 32'b0;
        MEM_WB_ALU_RES    <= 32'b0;
        MEM_WB_RD         <= 5'b0;
        MEM_WB_REG_WRITE  <= 1'b0;
        MEM_WB_MEM_TO_REG <= 1'b0;
    end else begin
        MEM_WB_MEM_DATA   <= mem_read_data;
        MEM_WB_ALU_RES    <= EX_MEM_ALU_RES;
        MEM_WB_RD         <= EX_MEM_RD;
        MEM_WB_REG_WRITE  <= EX_MEM_REG_WRITE;
        MEM_WB_MEM_TO_REG <= EX_MEM_MEM_TO_REG;
    end
end

// ============================================================
// WB Stage
// ============================================================
assign wb_data = MEM_WB_MEM_TO_REG ? MEM_WB_MEM_DATA : MEM_WB_ALU_RES;

// ============================================================
// LED Display with Switch Selection
// SW1 SW0 | Register | Value | LED
//  0   0  | x3 sum   |  8    | 1000
//  0   1  | x4 diff  |  2    | 0010
//  1   0  | x5 and   |  1    | 0001
//  1   1  | x6 or    |  7    | 0111
// ============================================================
reg [31:0] selected_reg;
always @(*) begin
    case (sw)
        2'b00: selected_reg = reg3_out;
        2'b01: selected_reg = reg4_out;
        2'b10: selected_reg = reg5_out;
        2'b11: selected_reg = reg6_out;
        default: selected_reg = reg3_out;
    endcase
end

assign led = selected_reg[3:0];

endmodule

Final.srcs/sources_1/new/tb_rv32i.v
`timescale 1ns / 1ps
module tb_rv32i;
    reg        clk, rst;
    reg  [1:0] sw;
    wire [3:0] led;

    rv32i_pipeline DUT (
        .clk(clk), .rst(rst),
        .sw(sw), .led(led)
    );

    initial clk = 0;
    always #5 clk = ~clk;

    initial begin
        $dumpfile("rv32i.vcd");
        $dumpvars(0, tb_rv32i);
        rst = 1; sw = 2'b00;
        #50; rst = 0;
        #50000;
        sw = 2'b00; #200;
        $display("SW=00 led=%b x3=%0d (sum,   expect 8)", led, DUT.RF.regs[3]);
        sw = 2'b01; #200;
        $display("SW=01 led=%b x4=%0d (diff,  expect 2)", led, DUT.RF.regs[4]);
        sw = 2'b10; #200;
        $display("SW=10 led=%b x5=%0d (and,   expect 1)", led, DUT.RF.regs[5]);
        sw = 2'b11; #200;
        $display("SW=11 led=%b x6=%0d (or,    expect 7)", led, DUT.RF.regs[6]);
        $display("x7=%0d (xor=6) x8=%0d (sll=10)", DUT.RF.regs[7], DUT.RF.regs[8]);
        $finish;
    end
endmodule

Final.sim/sim_1/behav/xsim/rv32i.vcd
$date
   Fri Apr  3 15:36:52 2026
$end
$version
  2019.2
$end
$timescale
  1ps
$end
$scope module tb_rv32i $end
$var reg 1 ! clk $end
$var reg 1 " rst $end
$var reg 2 # sw [1:0] $end
$var wire 4 $ led [3:0] $end
$scope module DUT $end
$var wire 1 % clk $end
$var wire 1 & rst $end
$var wire 2 ' sw [1:0] $end
$var wire 4 $ led [3:0] $end
$var reg 32 ( IF_ID_PC [31:0] $end
$var reg 32 ) IF_ID_IR [31:0] $end
$var reg 32 * ID_EX_PC [31:0] $end
$var reg 32 + ID_EX_RS1 [31:0] $end
$var reg 32 , ID_EX_RS2 [31:0] $end
$var reg 32 - ID_EX_IMM [31:0] $end
$var reg 5 . ID_EX_RD [4:0] $end
$var reg 5 / ID_EX_RS1_ADDR [4:0] $end
$var reg 5 0 ID_EX_RS2_ADDR [4:0] $end
$var reg 4 1 ID_EX_ALU_OP [3:0] $end
$var reg 1 2 ID_EX_ALU_SRC $end
$var reg 1 3 ID_EX_MEM_READ $end
$var reg 1 4 ID_EX_MEM_WRITE $end
$var reg 1 5 ID_EX_REG_WRITE $end
$var reg 1 6 ID_EX_MEM_TO_REG $end
$var reg 3 7 ID_EX_FUNCT3 [2:0] $end
$var reg 32 8 EX_MEM_ALU_RES [31:0] $end
$var reg 32 9 EX_MEM_RS2 [31:0] $end
$var reg 5 : EX_MEM_RD [4:0] $end
$var reg 1 ; EX_MEM_MEM_READ $end
$var reg 1 < EX_MEM_MEM_WRITE $end
$var reg 1 = EX_MEM_REG_WRITE $end
$var reg 1 > EX_MEM_MEM_TO_REG $end
$var reg 3 ? EX_MEM_FUNCT3 [2:0] $end
$var reg 1 @ EX_MEM_ZERO $end
$var reg 32 A MEM_WB_MEM_DATA [31:0] $end
$var reg 32 B MEM_WB_ALU_RES [31:0] $end
$var reg 5 C MEM_WB_RD [4:0] $end
$var reg 1 D MEM_WB_REG_WRITE $end
$var reg 1 E MEM_WB_MEM_TO_REG $end
$var wire 32 F pc_out [31:0] $end
$var wire 32 G pc_next [31:0] $end
$var wire 32 H pc_plus4 [31:0] $end
$var wire 32 I instr [31:0] $end
$var wire 32 J rs1_data [31:0] $end
$var wire 32 K rs2_data [31:0] $end
$var wire 32 L imm_ext [31:0] $end
$var wire 32 M alu_in_b [31:0] $end
$var wire 32 N alu_result [31:0] $end
$var wire 32 O mem_read_data [31:0] $end
$var wire 32 P wb_data [31:0] $end
$var wire 32 Q reg3_out [31:0] $end
$var wire 32 R reg4_out [31:0] $end
$var wire 32 S reg5_out [31:0] $end
$var wire 32 T reg6_out [31:0] $end
$var wire 32 U reg7_out [31:0] $end
$var wire 32 V reg8_out [31:0] $end
$var wire 1 W alu_zero $end
$var wire 4 X alu_ctrl [3:0] $end
$var wire 1 Y alu_src_ctrl $end
$var wire 1 Z mem_read_ctrl $end
$var wire 1 [ mem_write_ctrl $end
$var wire 1 \ reg_write_ctrl $end
$var wire 1 ] mem_to_reg_ctrl $end
$var wire 2 ^ forward_a [1:0] $end
$var wire 2 _ forward_b [1:0] $end
$var wire 1 ` stall $end
$var wire 5 a rd_id [4:0] $end
$var wire 5 b rs1_id [4:0] $end
$var wire 5 c rs2_id [4:0] $end
$var wire 3 d funct3 [2:0] $end
$var wire 7 e opcode [6:0] $end
$var wire 7 f funct7 [6:0] $end
$var wire 32 g fwd_rs1 [31:0] $end
$var wire 32 h fwd_rs2 [31:0] $end
$var reg 32 i selected_reg [31:0] $end
$scope module PC $end
$var wire 1 % clk $end
$var wire 1 & rst $end
$var wire 1 ` stall $end
$var wire 32 G pc_next [31:0] $end
$var reg 32 j pc_out [31:0] $end
$upscope $end
$scope module IMEM $end
$var wire 1 % clk $end
$var wire 32 F addr [31:0] $end
$var wire 32 I instr [31:0] $end
$var integer 32 k k $end
$upscope $end
$scope module RF $end
$var wire 1 % clk $end
$var wire 1 l we $end
$var wire 5 b rs1 [4:0] $end
$var wire 5 c rs2 [4:0] $end
$var wire 5 m rd [4:0] $end
$var wire 32 P wd [31:0] $end
$var wire 32 J rs1_data [31:0] $end
$var wire 32 K rs2_data [31:0] $end
$var wire 32 Q reg3_out [31:0] $end
$var wire 32 R reg4_out [31:0] $end
$var wire 32 S reg5_out [31:0] $end
$var wire 32 T reg6_out [31:0] $end
$var wire 32 U reg7_out [31:0] $end
$var wire 32 V reg8_out [31:0] $end
$var integer 32 n i $end
$upscope $end
$scope module IMMGEN $end
$var wire 32 o instr [31:0] $end
$var reg 32 p imm [31:0] $end
$var wire 7 q opcode [6:0] $end
$upscope $end
$scope module CU $end
$var wire 7 e opcode [6:0] $end
$var wire 7 f funct7 [6:0] $end
$var wire 3 d funct3 [2:0] $end
$var reg 4 r alu_op [3:0] $end
$var reg 1 s alu_src $end
$var reg 1 t mem_read $end
$var reg 1 u mem_write $end
$var reg 1 v reg_write $end
$var reg 1 w mem_to_reg $end
$upscope $end
$scope module HU $end
$var wire 1 x id_ex_mem_read $end
$var wire 5 y id_ex_rd [4:0] $end
$var wire 5 b if_id_rs1 [4:0] $end
$var wire 5 c if_id_rs2 [4:0] $end
$var wire 1 ` stall $end
$upscope $end
$scope module FU $end
$var wire 5 z ex_mem_rd [4:0] $end
$var wire 5 { mem_wb_rd [4:0] $end
$var wire 5 | id_ex_rs1 [4:0] $end
$var wire 5 } id_ex_rs2 [4:0] $end
$var wire 1 ~ ex_mem_reg_write $end
$var wire 1 !! mem_wb_reg_write $end
$var reg 2 "! forward_a [1:0] $end
$var reg 2 #! forward_b [1:0] $end
$upscope $end
$scope module ALU $end
$var wire 32 g a [31:0] $end
$var wire 32 M b [31:0] $end
$var wire 4 $! alu_ctrl [3:0] $end
$var reg 32 %! result [31:0] $end
$var wire 1 W zero $end
$upscope $end
$scope module DMEM $end
$var wire 1 % clk $end
$var wire 1 &! mem_read $end
$var wire 1 '! mem_write $end
$var wire 32 (! addr [31:0] $end
$var wire 32 )! wd [31:0] $end
$var wire 3 *! funct3 [2:0] $end
$var reg 32 +! rd [31:0] $end
$var integer 32 ,! i $end
$upscope $end
$upscope $end
$upscope $end
$enddefinitions $end
#0
$dumpvars
0!
0!!
1"
b0 "!
b0 #
b0 #!
b0 $
b0 $!
0%
b0 %!
1&
0&!
b0 '
0'!
b0 (
b0 (!
b10011 )
b0 )!
b0 *
b0 *!
b0 +
b0 +!
b0 ,
b100000000 ,!
b0 -
b0 .
b0 /
b0 0
b0 1
02
03
04
05
06
b0 7
b0 8
b0 9
b0 :
0;
0<
0=
0>
b0 ?
0@
b0 A
b0 B
b0 C
0D
0E
b0 F
b100 G
b100 H
b10100000000000010010011 I
b0 J
b0 K
b0 L
b0 M
b0 N
b0 O
b0 P
b0 Q
b0 R
b0 S
b0 T
b0 U
b0 V
1W
b0 X
1Y
0Z
0[
1\
0]
b0 ^
b0 _
0`
b0 a
b0 b
b0 c
b0 d
b10011 e
b0 f
b0 g
b0 h
b0 i
b0 j
b100000000 k
0l
b0 m
b100000 n
b10011 o
b0 p
b10011 q
b0 r
1s
0t
0u
1v
0w
0x
b0 y
b0 z
b0 {
b0 |
b0 }
0~
$end
#5000
1!
1%
#10000
0!
0%
#15000
1!
1%
#20000
0!
0%
#25000
1!
1%
#30000
0!
0%
#35000
1!
1%
#40000
0!
0%
#45000
1!
1%
#50000
0!
0"
0%
0&
#55000
1!
1%
b10100000000000010010011 )
12
15
1@
b100 F
b1000 G
b1000 H
b1100000000000100010011 I
b101 L
b0 M
b1 a
b101 c
b100 j
b10100000000000010010011 o
b101 p
#60000
0!
0%
#65000
1!
b0 "!
b0 #!
1%
b101 %!
b100 (
b1100000000000100010011 )
b101 -
b1 .
b101 0
1=
b1000 F
b1100 G
b1100 H
b1000001000000110110011 I
b11 L
b101 M
b101 N
0W
b10 a
b11 c
b1000 j
b1100000000000100010011 o
b11 p
b1 y
b101 }
1~
#70000
0!
0%
#75000
1!
1!!
b0 "!
b0 #!
1%
b11 %!
b1000 (
b101 (!
b1000001000000110110011 )
b100 *
b0 +!
b11 -
b10 .
b11 0
b101 8
b1 :
0@
1D
b1100 F
b10000 G
b10000 H
b1100000010000000100011 I
b0 L
b11 M
b11 N
0Y
b11 a
b1 b
b10 c
b110011 e
b0 g
b0 h
b1100 j
1l
b1000001000000110110011 o
b0 p
b110011 q
b0 r
0s
0t
0u
1v
0w
b10 y
b1 z
b11 }
#80000
0!
0%
#85000
1!
b1 "!
b10 #!
1%
b1000 %!
b1100 (
b11 (!
b1100000010000000100011 )
b1000 *
b0 +!
b0 -
b11 .
b1 /
b10 0
02
b11 8
b10 :
b101 B
b1 C
b10000 F
b10100 G
b10100 H
b10001000000011 I
b11 M
b1000 N
b101 P
0W
1Y
1[
0\
b1 ^
b10 _
b0 a
b0 b
b11 c
b10 d
b100011 e
b101 g
b11 h
b10000 j
b1 m
b1100000010000000100011 o
b0 p
b100011 q
b0 r
1s
0t
1u
0v
0w
b11 y
b10 z
b1 {
b1 |
b10 }
#90000
0!
0%
#95000
1!
b0 "!
b10 #!
1%
b0 %!
b10000 (
b1000 (!
b10001000000011 )
b11 )!
b1100 *
b0 +!
b0 .
b0 /
b11 0
12
14
05
b10 7
b1000 8
b11 9
b11 :
b11 B
b10 C
b10100 F
b11000 G
b11000 H
b10011 I
b0 M
b0 N
b11 P
1W
1Z
0[
1\
1]
b0 ^
b100 a
b0 c
b11 e
b0 g
b1000 h
b10100 j
b10 m
b10001000000011 o
b0 p
b11 q
b0 r
1s
1t
0u
1v
1w
b0 y
b11 z
b10 {
b0 |
b11 }
#100000
0!
0%
#105000
1!
b0 "!
b0 #!
1%
1'!
b10100 (
b0 (!
b10011 )
b1000 )!
b10000 *
b10 *!
b0 +!
b100 .
b0 0
13
04
15
16
b0 8
b1000 9
b0 :
1<
0=
b10 ?
1@
b1000 B
b11 C
b11000 F
b11100 G
b11100 H
b0 M
b1000 P
0Z
0]
b0 _
b0 a
b0 d
b10011 e
b0 g
b0 h
b11000 j
b11 m
b10011 o
b0 p
b10011 q
b0 r
1s
0t
0u
1v
0w
1x
b100 y
b0 z
b11 {
b0 }
0~
#110000
0!
0%
#115000
1!
0!!
b0 "!
b0 #!
b1000 $
1%
1&!
0'!
b11000 (
b0 )!
b10100 *
b1000 +!
b0 .
03
06
b0 7
b0 9
b100 :
1;
0<
1=
1>
b0 B
b0 C
0D
b11100 F
b100000 G
b100000 H
b1000 O
b0 P
b1000 Q
b0 g
b0 h
b1000 i
b11100 j
0l
b0 m
0x
b0 y
b100 z
b0 {
1~
#120000
0!
0%
#125000
1!
1!!
b0 "!
b0 #!
1%
0&!
b11100 (
b11000 *
b0 *!
b0 +!
b0 :
0;
0>
b0 ?
b1000 A
b100 C
1D
1E
b100000 F
b100100 G
b100100 H
b0 O
b1000 P
b0 g
b0 h
b100000 j
1l
b100 m
b0 z
b100 {
#130000
0!
0%
#135000
1!
b0 "!
b0 #!
1%
b100000 (
b11100 *
b0 A
b0 C
0E
b100100 F
b101000 G
b101000 H
b0 P
b1000 R
b0 g
b0 h
b1000 i
b100100 j
b0 m
b0 {
#140000
0!
0%
#145000
1!
1%
b100100 (
b100000 *
b101000 F
b101100 G
b101100 H
b101000 j
#150000
0!
0%
#155000
1!
1%
b101000 (
b100100 *
b101100 F
b110000 G
b110000 H
b101100 j
#160000
0!
0%
#165000
1!
1%
b101100 (
b101000 *
b110000 F
b110100 G
b110100 H
b110000 j
#170000
0!
0%
#175000
1!
1%
b110000 (
b101100 *
b110100 F
b111000 G
b111000 H
b110100 j
#180000
0!
0%
